electra_classifier/__init__.py
electra_classifier/model.py
electra_classifier-0.1.0.dist-info/METADATA
electra_classifier-0.1.0.dist-info/WHEEL
electra_classifier-0.1.0.dist-info/top_level.txt
electra_classifier-0.1.0.dist-info/RECORD
