Metadata-Version: 2.1
Name: electra-classifier
Version: 0.1.0
Summary: Electra Classifier for Sentiment Analysis
Home-page: https://github.com/jbeno/electra-classifier
Author: Jim Beno
Author-email: jim@jimbeno.net
License: MIT
Classifier: Programming Language :: Python :: 3
Requires-Dist: torch >=1.8.0
Requires-Dist: transformers >=4.5.0
